LICENSE
README.md
setup.py
fuck_god/__init__.py
fuck_god.egg-info/PKG-INFO
fuck_god.egg-info/SOURCES.txt
fuck_god.egg-info/dependency_links.txt
fuck_god.egg-info/top_level.txt