Metadata-Version: 2.1
Name: fuck-god
Version: 0.0.0
Summary: fuck_god
Home-page: https://github.com/Kaguya233qwq/fuck_god
Author: Kaguya233qwq
Author-email: 1435608435@qq.com
License: UNKNOWN
Keywords: fuck-god
Platform: any
Classifier: Programming Language :: Python :: 3
Classifier: License :: OSI Approved :: GNU General Public License v3 (GPLv3)
Classifier: Natural Language :: Chinese (Simplified)
License-File: LICENSE
